[
  {
    "team": "Green Bay Packers",
    "games": 17,
    "total_yards_to": {
      "points_allowed": 338,
      "yards": 5347,
      "plays": 1036,
      "yards_per_play": 5.2,
      "turnovers": 31,
      "fumbles_lost": 14,
      "first_downs": 327
    },
    "passing": {
      "completions": 381,
      "attempts": 565,
      "yards": 3658,
      "touchdowns": 23,
      "interceptions": 17,
      "net_yards_per_attempt": 6.0,
      "first_downs": 200
    },
    "rushing": {
      "attempts": 426,
      "yards": 1689,
      "touchdowns": 13,
      "yards_per_attempt": 4.0,
      "first_downs": 104
    },
    "penalties": {
      "penalties": 114,
      "yards": 940,
      "first_downs_by_penalty": 23
    },
    "other": {
      "scoring_percentage": 33.0,
      "turnover_percentage": 16.2,
      "expected_points": 10.82
    },
    "advanced_defense": {
      "attempts": 565,
      "completions": 381,
      "yards": 3658,
      "touchdowns": 23,
      "dadot": 7.3,
      "air_yards": 2128,
      "yards_after_catch": 1921,
      "blitzes": 112,
      "blitz_percentage": 17.3,
      "hurries": 55,
      "hurry_percentage": 8.5,
      "qb_knockdowns": 43,
      "qb_knockdown_percentage": 7.6,
      "sacks": 45,
      "pressures": 143,
      "pressure_percentage": 22.1,
      "missed_tackles": 108
    },
    "conversions_against": {
      "third_down_attempts": 208,
      "third_down_conversions": 78,
      "third_down_percentage": 37.5,
      "fourth_down_attempts": 30,
      "fourth_down_conversions": 18,
      "fourth_down_percentage": 60.0,
      "red_zone_attempts": 50,
      "red_zone_touchdowns": 30,
      "red_zone_percentage": 60.0
    },
    "scoring_defense": {
      "rushing_touchdowns": 13,
      "receiving_touchdowns": 23,
      "punt_return_touchdowns": 1,
      "kick_return_touchdowns": 0,
      "fumble_touchdowns": 0,
      "interception_touchdowns": 2,
      "other_touchdowns": 0,
      "total_touchdowns": 39,
      "two_point_makes": 1,
      "two_point_attempts": 5,
      "defensive_two_point": 0,
      "extra_point_makes": 33,
      "extra_point_attempts": 34,
      "field_goal_makes": 23,
      "field_goal_attempts": 27,
      "safeties": 0,
      "points": 338,
      "points_per_game": 19.9
    }
  },
  {
    "team": "Detroit Lions",
    "games": 17,
    "total_yards_to": {
      "points_allowed": 342,
      "yards": 5820,
      "plays": 1016,
      "yards_per_play": 5.7,
      "turnovers": 24,
      "fumbles_lost": 8,
      "first_downs": 331
    },
    "passing": {
      "completions": 373,
      "attempts": 610,
      "yards": 4148,
      "touchdowns": 18,
      "interceptions": 16,
      "net_yards_per_attempt": 6.4,
      "first_downs": 198
    },
    "rushing": {
      "attempts": 369,
      "yards": 1672,
      "touchdowns": 18,
      "yards_per_attempt": 4.5,
      "first_downs": 86
    },
    "penalties": {
      "penalties": 114,
      "yards": 862,
      "first_downs_by_penalty": 47
    },
    "other": {
      "scoring_percentage": 35.4,
      "turnover_percentage": 13.3,
      "expected_points": -58.06
    },
    "advanced_defense": {
      "attempts": 610,
      "completions": 373,
      "yards": 4148,
      "touchdowns": 18,
      "dadot": 9.0,
      "air_yards": 2542,
      "yards_after_catch": 2106,
      "blitzes": 237,
      "blitz_percentage": 34.6,
      "hurries": 73,
      "hurry_percentage": 10.7,
      "qb_knockdowns": 69,
      "qb_knockdown_percentage": 11.3,
      "sacks": 37,
      "pressures": 179,
      "pressure_percentage": 26.2,
      "missed_tackles": 85
    },
    "conversions_against": {
      "third_down_attempts": 185,
      "third_down_conversions": 60,
      "third_down_percentage": 32.4,
      "fourth_down_attempts": 29,
      "fourth_down_conversions": 12,
      "fourth_down_percentage": 41.4,
      "red_zone_attempts": 55,
      "red_zone_touchdowns": 28,
      "red_zone_percentage": 50.9
    },
    "scoring_defense": {
      "rushing_touchdowns": 18,
      "receiving_touchdowns": 18,
      "punt_return_touchdowns": 0,
      "kick_return_touchdowns": 0,
      "fumble_touchdowns": 1,
      "interception_touchdowns": 0,
      "other_touchdowns": 0,
      "total_touchdowns": 37,
      "two_point_makes": 1,
      "two_point_attempts": 4,
      "defensive_two_point": 0,
      "extra_point_makes": 32,
      "extra_point_attempts": 33,
      "field_goal_makes": 28,
      "field_goal_attempts": 35,
      "safeties": 1,
      "points": 342,
      "points_per_game": 20.1
    }
  },
  {
    "team": "Pittsburgh Steelers",
    "games": 17,
    "total_yards_to": {
      "points_allowed": 347,
      "yards": 5554,
      "plays": 1034,
      "yards_per_play": 5.4,
      "turnovers": 33,
      "fumbles_lost": 16,
      "first_downs": 324
    },
    "passing": {
      "completions": 382,
      "attempts": 582,
      "yards": 3876,
      "touchdowns": 23,
      "interceptions": 17,
      "net_yards_per_attempt": 6.2,
      "first_downs": 193
    },
    "rushing": {
      "attempts": 412,
      "yards": 1678,
      "touchdowns": 14,
      "yards_per_attempt": 4.1,
      "first_downs": 108
    },
    "penalties": {
      "penalties": 125,
      "yards": 1039,
      "first_downs_by_penalty": 23
    },
    "other": {
      "scoring_percentage": 34.6,
      "turnover_percentage": 15.9,
      "expected_points": -34.89
    },
    "advanced_defense": {
      "attempts": 582,
      "completions": 382,
      "yards": 3876,
      "touchdowns": 23,
      "dadot": 7.2,
      "air_yards": 2278,
      "yards_after_catch": 2048,
      "blitzes": 165,
      "blitz_percentage": 25.9,
      "hurries": 37,
      "hurry_percentage": 5.8,
      "qb_knockdowns": 63,
      "qb_knockdown_percentage": 10.8,
      "sacks": 40,
      "pressures": 140,
      "pressure_percentage": 22.0,
      "missed_tackles": 69
    },
    "conversions_against": {
      "third_down_attempts": 204,
      "third_down_conversions": 72,
      "third_down_percentage": 35.3,
      "fourth_down_attempts": 22,
      "fourth_down_conversions": 15,
      "fourth_down_percentage": 68.2,
      "red_zone_attempts": 61,
      "red_zone_touchdowns": 33,
      "red_zone_percentage": 54.1
    },
    "scoring_defense": {
      "rushing_touchdowns": 14,
      "receiving_touchdowns": 23,
      "punt_return_touchdowns": 0,
      "kick_return_touchdowns": 0,
      "fumble_touchdowns": 0,
      "interception_touchdowns": 2,
      "other_touchdowns": 0,
      "total_touchdowns": 39,
      "two_point_makes": 2,
      "two_point_attempts": 7,
      "defensive_two_point": 0,
      "extra_point_makes": 31,
      "extra_point_attempts": 32,
      "field_goal_makes": 26,
      "field_goal_attempts": 33,
      "safeties": 0,
      "points": 347,
      "points_per_game": 20.4
    }
  },
  {
    "team": "Baltimore Ravens",
    "games": 17,
    "total_yards_to": {
      "points_allowed": 361,
      "yards": 5511,
      "plays": 1062,
      "yards_per_play": 5.2,
      "turnovers": 17,
      "fumbles_lost": 5,
      "first_downs": 330
    },
    "passing": {
      "completions": 396,
      "attempts": 625,
      "yards": 4150,
      "touchdowns": 27,
      "interceptions": 12,
      "net_yards_per_attempt": 6.1,
      "first_downs": 218
    },
    "rushing": {
      "attempts": 383,
      "yards": 1361,
      "touchdowns": 12,
      "yards_per_attempt": 3.6,
      "first_downs": 69
    },
    "penalties": {
      "penalties": 97,
      "yards": 759,
      "first_downs_by_penalty": 43
    },
    "other": {
      "scoring_percentage": 36.6,
      "turnover_percentage": 9.1,
      "expected_points": -49.44
    },
    "advanced_defense": {
      "attempts": 625,
      "completions": 396,
      "yards": 4150,
      "touchdowns": 27,
      "dadot": 8.2,
      "air_yards": 2728,
      "yards_after_catch": 2030,
      "blitzes": 143,
      "blitz_percentage": 20.3,
      "hurries": 44,
      "hurry_percentage": 6.2,
      "qb_knockdowns": 61,
      "qb_knockdown_percentage": 9.8,
      "sacks": 54,
      "pressures": 159,
      "pressure_percentage": 22.5,
      "missed_tackles": 76
    },
    "conversions_against": {
      "third_down_attempts": 226,
      "third_down_conversions": 90,
      "third_down_percentage": 39.8,
      "fourth_down_attempts": 28,
      "fourth_down_conversions": 12,
      "fourth_down_percentage": 42.9,
      "red_zone_attempts": 50,
      "red_zone_touchdowns": 27,
      "red_zone_percentage": 54.0
    },
    "scoring_defense": {
      "rushing_touchdowns": 12,
      "receiving_touchdowns": 27,
      "punt_return_touchdowns": 0,
      "kick_return_touchdowns": 0,
      "fumble_touchdowns": 0,
      "interception_touchdowns": 0,
      "other_touchdowns": 0,
      "total_touchdowns": 39,
      "two_point_makes": 2,
      "two_point_attempts": 7,
      "defensive_two_point": 0,
      "extra_point_makes": 32,
      "extra_point_attempts": 32,
      "field_goal_makes": 29,
      "field_goal_attempts": 33,
      "safeties": 2,
      "points": 361,
      "points_per_game": 21.2
    }
  },
  {
    "team": "Arizona Cardinals",
    "games": 17,
    "total_yards_to": {
      "points_allowed": 379,
      "yards": 5823,
      "plays": 1045,
      "yards_per_play": 5.6,
      "turnovers": 17,
      "fumbles_lost": 8,
      "first_downs": 344
    },
    "passing": {
      "completions": 370,
      "attempts": 539,
      "yards": 3674,
      "touchdowns": 20,
      "interceptions": 9,
      "net_yards_per_attempt": 6.3,
      "first_downs": 200
    },
    "rushing": {
      "attempts": 465,
      "yards": 2149,
      "touchdowns": 18,
      "yards_per_attempt": 4.6,
      "first_downs": 124
    },
    "penalties": {
      "penalties": 100,
      "yards": 803,
      "first_downs_by_penalty": 20
    },
    "other": {
      "scoring_percentage": 43.1,
      "turnover_percentage": 9.6,
      "expected_points": -110.14
    },
    "advanced_defense": {
      "attempts": 539,
      "completions": 370,
      "yards": 3674,
      "touchdowns": 20,
      "dadot": 7.0,
      "air_yards": 1973,
      "yards_after_catch": 1945,
      "blitzes": 134,
      "blitz_percentage": 21.6,
      "hurries": 44,
      "hurry_percentage": 7.1,
      "qb_knockdowns": 34,
      "qb_knockdown_percentage": 6.3,
      "sacks": 41,
      "pressures": 119,
      "pressure_percentage": 19.2,
      "missed_tackles": 106
    },
    "conversions_against": {
      "third_down_attempts": 208,
      "third_down_conversions": 91,
      "third_down_percentage": 43.8,
      "fourth_down_attempts": 24,
      "fourth_down_conversions": 14,
      "fourth_down_percentage": 58.3,
      "red_zone_attempts": 57,
      "red_zone_touchdowns": 30,
      "red_zone_percentage": 52.6
    },
    "scoring_defense": {
      "rushing_touchdowns": 18,
      "receiving_touchdowns": 20,
      "punt_return_touchdowns": 0,
      "kick_return_touchdowns": 0,
      "fumble_touchdowns": 0,
      "interception_touchdowns": 1,
      "other_touchdowns": 1,
      "total_touchdowns": 40,
      "two_point_makes": 1,
      "two_point_attempts": 1,
      "defensive_two_point": 0,
      "extra_point_makes": 35,
      "extra_point_attempts": 38,
      "field_goal_makes": 34,
      "field_goal_attempts": 38,
      "safeties": 0,
      "points": 379,
      "points_per_game": 22.3
    },
  [
